dbcenter-0.1.0.dist-info/METADATA
dbcenter-0.1.0.dist-info/WHEEL
dbcenter/__init__.py
dbcenter/dbcenter.pyd
dbcenter-0.1.0.dist-info/RECORD
