Metadata-Version: 2.4
Name: dbcenter
Version: 0.1.0
Classifier: Programming Language :: Rust
Classifier: Programming Language :: Python :: 3
Classifier: License :: OSI Approved :: MIT License
Requires-Dist: pytest ; extra == 'dev'
Requires-Dist: pandas ; extra == 'dev'
Provides-Extra: dev
Summary: Embedded PostgreSQL with MongoDB-style API - Rust Edition
Author-email: DB Architect <arch@db.center>
Requires-Python: >=3.8
